larq/__init__.py
larq/activations.py
larq/activations_test.py
larq/callbacks.py
larq/callbacks_test.py
larq/conftest.py
larq/conftest_test.py
larq/constraints.py
larq/constraints_test.py
larq/context.py
larq/context_test.py
larq/layers.py
larq/layers_base.py
larq/layers_test.py
larq/math.py
larq/math_test.py
larq/metrics.py
larq/metrics_test.py
larq/models.py
larq/models_test.py
larq/optimizers.py
larq/optimizers_test.py
larq/quantized_variable.py
larq/quantized_variable_test.py
larq/quantizers.py
larq/quantizers_test.py
larq/testing_utils.py
larq/utils.py
larq/utils_test.py
larq/version_test.py
larq-0.13.3.dist-info/LICENSE
larq-0.13.3.dist-info/METADATA
larq-0.13.3.dist-info/WHEEL
larq-0.13.3.dist-info/top_level.txt
larq-0.13.3.dist-info/RECORD
