Metadata-Version: 2.1
Name: larq
Version: 0.13.3
Summary: An Open Source Machine Learning Library for Training Binarized Neural Networks
Home-page: https://larq.dev/
Author: Plumerai
Author-email: opensource@plumerai.com
License: Apache 2.0
Classifier: Development Status :: 4 - Beta
Classifier: Intended Audience :: Developers
Classifier: Intended Audience :: Education
Classifier: Intended Audience :: Science/Research
Classifier: License :: OSI Approved :: Apache Software License
Classifier: Programming Language :: Python :: 3
Classifier: Programming Language :: Python :: 3 :: Only
Classifier: Programming Language :: Python :: 3.7
Classifier: Programming Language :: Python :: 3.8
Classifier: Programming Language :: Python :: 3.9
Classifier: Programming Language :: Python :: 3.10
Classifier: Topic :: Scientific/Engineering
Classifier: Topic :: Scientific/Engineering :: Mathematics
Classifier: Topic :: Scientific/Engineering :: Artificial Intelligence
Classifier: Topic :: Software Development
Classifier: Topic :: Software Development :: Libraries
Classifier: Topic :: Software Development :: Libraries :: Python Modules
Requires-Python: >=3.7
License-File: LICENSE
Requires-Dist: numpy (<2.0,>=1.15.4)
Requires-Dist: terminaltables (>=3.1.0)
Requires-Dist: packaging (>=19.2)
Requires-Dist: importlib-metadata (<4.0,>=2.0) ; python_version < "3.8"
Provides-Extra: lint
Requires-Dist: black (==23.7.0) ; extra == 'lint'
Requires-Dist: flake8 (==6.0.*) ; extra == 'lint'
Requires-Dist: isort (==5.11.*) ; extra == 'lint'
Requires-Dist: pytype (==2022.10.26) ; extra == 'lint'
Provides-Extra: tensorflow
Requires-Dist: tensorflow (>=1.14.0) ; extra == 'tensorflow'
Provides-Extra: tensorflow_gpu
Requires-Dist: tensorflow-gpu (>=1.14.0) ; extra == 'tensorflow_gpu'
Provides-Extra: test
Requires-Dist: pytest (==7.4.*) ; extra == 'test'
Requires-Dist: pytest-cov (<4.2,>=4.0) ; extra == 'test'
Requires-Dist: pytest-xdist (==3.2.*) ; extra == 'test'
Requires-Dist: pytest-mock (==3.11.*) ; extra == 'test'
Requires-Dist: snapshottest (==0.6.*) ; extra == 'test'
